core_evals/vlmevalkit/__init__.py
core_evals/vlmevalkit/framework.yml
core_evals/vlmevalkit/framework_entrypoint.py
core_evals/vlmevalkit/output.py
nvidia_vlmeval-25.11.dist-info/licenses/LICENSE
vlmeval/__init__.py
vlmeval/config.py
vlmeval/inference.py
vlmeval/inference_mt.py
vlmeval/inference_video.py
vlmeval/run.py
vlmeval/tools.py
vlmeval/api/__init__.py
vlmeval/api/bailingmm.py
vlmeval/api/base.py
vlmeval/api/bluelm_v_api.py
vlmeval/api/claude.py
vlmeval/api/cloudwalk.py
vlmeval/api/doubao_vl_api.py
vlmeval/api/gemini.py
vlmeval/api/glm_vision.py
vlmeval/api/gpt.py
vlmeval/api/hf_chat_model.py
vlmeval/api/hunyuan.py
vlmeval/api/jt_vl_chat.py
vlmeval/api/lmdeploy.py
vlmeval/api/mug_u.py
vlmeval/api/oai.py
vlmeval/api/qwen_api.py
vlmeval/api/qwen_vl_api.py
vlmeval/api/reka.py
vlmeval/api/sensechat_vision.py
vlmeval/api/siliconflow.py
vlmeval/api/stepai.py
vlmeval/api/taichu.py
vlmeval/api/taiyi.py
vlmeval/dataset/__init__.py
vlmeval/dataset/cgbench.py
vlmeval/dataset/cmmmu.py
vlmeval/dataset/creation.py
vlmeval/dataset/dude.py
vlmeval/dataset/dynamath.py
vlmeval/dataset/emma.py
vlmeval/dataset/image_base.py
vlmeval/dataset/image_caption.py
vlmeval/dataset/image_ccocr.py
vlmeval/dataset/image_mcq.py
vlmeval/dataset/image_mt.py
vlmeval/dataset/image_shortqa.py
vlmeval/dataset/image_vqa.py
vlmeval/dataset/image_yorn.py
vlmeval/dataset/longvideobench.py
vlmeval/dataset/megabench.py
vlmeval/dataset/miabench.py
vlmeval/dataset/mlvu.py
vlmeval/dataset/mmalignbench.py
vlmeval/dataset/mmbench_video.py
vlmeval/dataset/mmgenbench.py
vlmeval/dataset/mmlongbench.py
vlmeval/dataset/mmmath.py
vlmeval/dataset/moat.py
vlmeval/dataset/moviechat1k.py
vlmeval/dataset/mvbench.py
vlmeval/dataset/qbench_video.py
vlmeval/dataset/slidevqa.py
vlmeval/dataset/tamperbench.py
vlmeval/dataset/tempcompass.py
vlmeval/dataset/text_base.py
vlmeval/dataset/text_mcq.py
vlmeval/dataset/vcr.py
vlmeval/dataset/vdc.py
vlmeval/dataset/video_base.py
vlmeval/dataset/video_concat_dataset.py
vlmeval/dataset/video_dataset_config.py
nvidia_vlmeval-25.11.dist-info/METADATA
nvidia_vlmeval-25.11.dist-info/WHEEL
nvidia_vlmeval-25.11.dist-info/entry_points.txt
nvidia_vlmeval-25.11.dist-info/top_level.txt
nvidia_vlmeval-25.11.dist-info/RECORD
