Metadata-Version: 2.4
Name: nvidia-vlmeval
Version: 25.11
Summary: OpenCompass VLM Evaluation Kit - packaged by NVIDIA
Keywords: AI,NLP,in-context learning
Classifier: Development Status :: 5 - Production/Stable
Classifier: Programming Language :: Python :: 3
Classifier: License :: OSI Approved :: Apache Software License
Classifier: Operating System :: OS Independent
Requires-Python: >=3.7.0
License-File: LICENSE
Requires-Dist: decord; platform_machine != "arm64"
Requires-Dist: eva-decord; platform_machine == "arm64"
Requires-Dist: gradio
Requires-Dist: huggingface_hub
Requires-Dist: imageio
Requires-Dist: matplotlib
Requires-Dist: numpy
Requires-Dist: omegaconf
Requires-Dist: openai
Requires-Dist: opencv-python>=4.4.0.46
Requires-Dist: openpyxl
Requires-Dist: pandas
Requires-Dist: pillow
Requires-Dist: portalocker
Requires-Dist: protobuf
Requires-Dist: python-dotenv
Requires-Dist: requests
Requires-Dist: rich
Requires-Dist: sentencepiece
Requires-Dist: setuptools
Requires-Dist: sty
Requires-Dist: tabulate
Requires-Dist: tiktoken
Requires-Dist: timeout-decorator
Requires-Dist: torch
Requires-Dist: torchvision
Requires-Dist: tqdm
Requires-Dist: transformers
Requires-Dist: typing_extensions
Requires-Dist: validators
Requires-Dist: xlsxwriter<=3.2.3
Requires-Dist: nemo-evaluator
Dynamic: classifier
Dynamic: description
Dynamic: description-content-type
Dynamic: keywords
Dynamic: license-file
Dynamic: requires-dist
Dynamic: requires-python
Dynamic: summary
